src/sop_deutils/__init__.py
src/sop_deutils/y4a_airflow.py
src/sop_deutils/y4a_retry.py
src/sop_deutils/y4a_telegram.py
src/sop_deutils/datalake/y4a_minio.py
src/sop_deutils/gg_api/y4a_sheet.py
src/sop_deutils/sql/y4a_monitor_user_external.py
src/sop_deutils/sql/y4a_postgresql.py
sop_deutils_demo-0.1.5.dist-info/METADATA
sop_deutils_demo-0.1.5.dist-info/WHEEL
sop_deutils_demo-0.1.5.dist-info/licenses/LICENSE
sop_deutils_demo-0.1.5.dist-info/RECORD
