Metadata-Version: 2.1
Name: sop_deutils_demo
Version: 0.1.5
Summary: A utils package for Yes4All SOP
Project-URL: Author_Github, https://github.com/dribblewithclong
Author-email: liuliukiki <longnc@yes4all.com>
License-File: LICENSE
Classifier: License :: OSI Approved :: MIT License
Classifier: Operating System :: OS Independent
Classifier: Programming Language :: Python :: 3
Requires-Python: >=3.7
Requires-Dist: aiofiles>=23.2.1
Requires-Dist: fastparquet>=2023.8.0
Requires-Dist: gspread>=5.11.3
Requires-Dist: lxml>=4.9.3
Requires-Dist: minio>=7.1.17
Requires-Dist: openpyxl>=3.1.2
Requires-Dist: pandas>=2.1.1
Requires-Dist: psycopg2-binary>=2.9.9
Requires-Dist: pyarrow>=13.0.0
Requires-Dist: python-telegram-bot>=20.6
Requires-Dist: pytz>=2023.3
Requires-Dist: requests>=2.31.0
Requires-Dist: sqlalchemy>=2.0.21
